goodmake.py
goodmake-0.2.0.data/scripts/goodmake_clean.sh
goodmake-0.2.0.data/scripts/goodmake_every.sh
goodmake-0.2.0.data/scripts/goodmake_lib.sh
goodmake-0.2.0.dist-info/DESCRIPTION.rst
goodmake-0.2.0.dist-info/METADATA
goodmake-0.2.0.dist-info/RECORD
goodmake-0.2.0.dist-info/WHEEL
goodmake-0.2.0.dist-info/entry_points.txt
goodmake-0.2.0.dist-info/metadata.json
goodmake-0.2.0.dist-info/top_level.txt
