Metadata-Version: 2.0
Name: goodmake
Version: 0.2.0
Summary: A simpler build system
Home-page: https://github.com/AmesCornish/GoodMake
Author: Ames Cornish
Author-email: goodmake@montebellopartners.com
License: GPLv3
Keywords: make,build,redo
Platform: UNKNOWN
Requires-Python: >=3.6
